adafruit_ov2640.py
adafruit_circuitpython_ov2640-1.2.9.dist-info/licenses/LICENSE
adafruit_circuitpython_ov2640-1.2.9.dist-info/METADATA
adafruit_circuitpython_ov2640-1.2.9.dist-info/WHEEL
adafruit_circuitpython_ov2640-1.2.9.dist-info/top_level.txt
adafruit_circuitpython_ov2640-1.2.9.dist-info/RECORD
